LICENSE
MANIFEST.in
README.rst
modbus.1
setup.cfg
setup.py
modbus/__init__.py
modbus/__main__.py
modbus_cli/__init__.py
modbus_cli/access.py
modbus_cli/definitions.py
modbus_cli/modbus_rtu.py
modbus_cli/modbus_tcp.py
modbus_cli.egg-info/PKG-INFO
modbus_cli.egg-info/SOURCES.txt
modbus_cli.egg-info/dependency_links.txt
modbus_cli.egg-info/entry_points.txt
modbus_cli.egg-info/not-zip-safe
modbus_cli.egg-info/requires.txt
modbus_cli.egg-info/top_level.txt
tests/simple.modbus
tests/test_access.py
tests/test_definitions.py