Metadata-Version: 2.1
Name: modbus_cli
Version: 0.1.10
Summary: Command line tool to access Modbus devices
Home-page: http://github.com/favalex/modbus-cli
Author: Gabriele Favalessa
Author-email: favalex@gmail.com
License: MPL 2.0
Classifier: Development Status :: 4 - Beta
Classifier: Environment :: Console
Classifier: Intended Audience :: End Users/Desktop
Classifier: License :: OSI Approved :: Mozilla Public License 2.0 (MPL 2.0)
Classifier: Operating System :: OS Independent
Classifier: Programming Language :: Python :: 3
Classifier: Topic :: Utilities
License-File: LICENSE
Requires-Dist: umodbus
Requires-Dist: colorama
